marshmallow_sa_core/__init__.py
marshmallow_sa_core/ma_sa_core.py
marshmallow_sa_core/table_schema.py
marshmallow_sa_core/testing.py
marshmallow_sa_core/utilities/__init__.py
marshmallow_sa_core/utilities/const.py
marshmallow_sa_core/utilities/enum.py
marshmallow_sa_core/utilities/schema.py
marshmallow_sa_core-0.0.5.dist-info/LICENSE
marshmallow_sa_core-0.0.5.dist-info/METADATA
marshmallow_sa_core-0.0.5.dist-info/WHEEL
marshmallow_sa_core-0.0.5.dist-info/top_level.txt
marshmallow_sa_core-0.0.5.dist-info/RECORD
