Metadata-Version: 2.1
Name: marshmallow-sa-core
Version: 0.0.5
Summary: SQLAlchemy-core integration with marshmallow
Home-page: https://github.com/featureoverload/marshmallow-sa-core
Author: Feature Overload
Author-email: featureoverload@gmail.com
License: MIT License
Platform: UNKNOWN
Requires-Python: >=3.8
License-File: LICENSE
Requires-Dist: marshmallow (>=3.13.0)
Requires-Dist: marshmallow-enum (>=1.5.1)
Requires-Dist: SQLAlchemy (>=1.4.0.*)
Provides-Extra: all
Requires-Dist: pytest (>=6.2.5) ; extra == 'all'
Requires-Dist: sphinx ; extra == 'all'
Requires-Dist: sphinx-rtd-theme (>=1.0.0) ; extra == 'all'
Requires-Dist: recommonmark (>=0.7.1) ; extra == 'all'
Provides-Extra: docs
Requires-Dist: sphinx ; extra == 'docs'
Requires-Dist: sphinx-rtd-theme (>=1.0.0) ; extra == 'docs'
Requires-Dist: recommonmark (>=0.7.1) ; extra == 'docs'
Provides-Extra: test
Requires-Dist: pytest (>=6.2.5) ; extra == 'test'
